GaosuShangShouC111417/README.md
GaosuShangShouC111417/__init__.py
GaosuShangShouC111417/__main__.py
GaosuShangShouC111417/file.pdf
GaosuShangShouC111417/index.html
gaosu_shang_shou_c_11_14_17-2024.3.3.0.dist-info/METADATA
gaosu_shang_shou_c_11_14_17-2024.3.3.0.dist-info/WHEEL
gaosu_shang_shou_c_11_14_17-2024.3.3.0.dist-info/entry_points.txt
gaosu_shang_shou_c_11_14_17-2024.3.3.0.dist-info/top_level.txt
gaosu_shang_shou_c_11_14_17-2024.3.3.0.dist-info/RECORD
